whatsapp_api_py-1.0.3.dist-info/licenses/LICENSE
whatsapp_api_wrapper/__init__.py
whatsapp_api_wrapper/client.py
whatsapp_api_wrapper/exceptions.py
whatsapp_api_wrapper/models.py
whatsapp_api_wrapper/py.typed
whatsapp_api_wrapper/utils.py
whatsapp_api_py-1.0.3.dist-info/METADATA
whatsapp_api_py-1.0.3.dist-info/WHEEL
whatsapp_api_py-1.0.3.dist-info/top_level.txt
whatsapp_api_py-1.0.3.dist-info/RECORD
